<annotation>
	<folder>VOC2007</folder>
	<filename>levle1_114.jpg</filename>
	<source>
		<database>My Database</database>
		<annotation>VOC2007</annotation>
		<image>flickr</image>
		<flickrid>NULL</flickrid>
	</source>
	<owner>
		<flickrid>NULL</flickrid>
		<name>xiaoxianyu</name>
	</owner>
	<size>
		<width>4912</width>
		<height>3264</height>
		<depth>3</depth>
	</size>
	<segmented>0</segmented>
	<object>
		<name>fore</name>
		<pose>Unspecified</pose>
		<truncated>0</truncated>
		<difficult>0</difficult>
		<bndbox>
			<xmin>3356</xmin>
			<ymin>1028</ymin>
			<xmax>3506</xmax>
			<ymax>1186</ymax>
		</bndbox>
	</object>
	<object>
		<name>fore</name>
		<pose>Unspecified</pose>
		<truncated>0</truncated>
		<difficult>0</difficult>
		<bndbox>
			<xmin>2633</xmin>
			<ymin>770</ymin>
			<xmax>2708</xmax>
			<ymax>895</ymax>
		</bndbox>
	</object>
	<object>
		<name>fore</name>
		<pose>Unspecified</pose>
		<truncated>0</truncated>
		<difficult>0</difficult>
		<bndbox>
			<xmin>3315</xmin>
			<ymin>1468</ymin>
			<xmax>3423</xmax>
			<ymax>1618</ymax>
		</bndbox>
	</object>
	<object>
		<name>fore</name>
		<pose>Unspecified</pose>
		<truncated>0</truncated>
		<difficult>0</difficult>
		<bndbox>
			<xmin>3439</xmin>
			<ymin>1693</ymin>
			<xmax>3556</xmax>
			<ymax>1851</ymax>
		</bndbox>
	</object>
	<object>
		<name>fore</name>
		<pose>Unspecified</pose>
		<truncated>0</truncated>
		<difficult>0</difficult>
		<bndbox>
			<xmin>2999</xmin>
			<ymin>1884</ymin>
			<xmax>3099</xmax>
			<ymax>2009</ymax>
		</bndbox>
	</object>
	<object>
		<name>fore</name>
		<pose>Unspecified</pose>
		<truncated>0</truncated>
		<difficult>0</difficult>
		<bndbox>
			<xmin>2891</xmin>
			<ymin>1801</ymin>
			<xmax>2974</xmax>
			<ymax>1950</ymax>
		</bndbox>
	</object>
	<object>
		<name>fore</name>
		<pose>Unspecified</pose>
		<truncated>0</truncated>
		<difficult>0</difficult>
		<bndbox>
			<xmin>2866</xmin>
			<ymin>2316</ymin>
			<xmax>3024</xmax>
			<ymax>2482</ymax>
		</bndbox>
	</object>
	<object>
		<name>fore</name>
		<pose>Unspecified</pose>
		<truncated>0</truncated>
		<difficult>0</difficult>
		<bndbox>
			<xmin>2874</xmin>
			<ymin>2640</ymin>
			<xmax>2999</xmax>
			<ymax>2765</ymax>
		</bndbox>
	</object>
	<object>
		<name>fore</name>
		<pose>Unspecified</pose>
		<truncated>0</truncated>
		<difficult>0</difficult>
		<bndbox>
			<xmin>3065</xmin>
			<ymin>2549</ymin>
			<xmax>3207</xmax>
			<ymax>2632</ymax>
		</bndbox>
	</object>
	<object>
		<name>fore</name>
		<pose>Unspecified</pose>
		<truncated>0</truncated>
		<difficult>0</difficult>
		<bndbox>
			<xmin>3099</xmin>
			<ymin>2632</ymin>
			<xmax>3240</xmax>
			<ymax>2740</ymax>
		</bndbox>
	</object>
	<object>
		<name>fore</name>
		<pose>Unspecified</pose>
		<truncated>0</truncated>
		<difficult>0</difficult>
		<bndbox>
			<xmin>3306</xmin>
			<ymin>2432</ymin>
			<xmax>3456</xmax>
			<ymax>2541</ymax>
		</bndbox>
	</object>
	<object>
		<name>fore</name>
		<pose>Unspecified</pose>
		<truncated>0</truncated>
		<difficult>0</difficult>
		<bndbox>
			<xmin>3406</xmin>
			<ymin>2524</ymin>
			<xmax>3514</xmax>
			<ymax>2632</ymax>
		</bndbox>
	</object>
	<object>
		<name>fore</name>
		<pose>Unspecified</pose>
		<truncated>0</truncated>
		<difficult>0</difficult>
		<bndbox>
			<xmin>3531</xmin>
			<ymin>2474</ymin>
			<xmax>3664</xmax>
			<ymax>2624</ymax>
		</bndbox>
	</object>
	<object>
		<name>fore</name>
		<pose>Unspecified</pose>
		<truncated>0</truncated>
		<difficult>0</difficult>
		<bndbox>
			<xmin>3298</xmin>
			<ymin>2233</ymin>
			<xmax>3389</xmax>
			<ymax>2399</ymax>
		</bndbox>
	</object>
	<object>
		<name>fore</name>
		<pose>Unspecified</pose>
		<truncated>0</truncated>
		<difficult>0</difficult>
		<bndbox>
			<xmin>3198</xmin>
			<ymin>2258</ymin>
			<xmax>3273</xmax>
			<ymax>2399</ymax>
		</bndbox>
	</object>
	<object>
		<name>fore</name>
		<pose>Unspecified</pose>
		<truncated>0</truncated>
		<difficult>0</difficult>
		<bndbox>
			<xmin>3448</xmin>
			<ymin>1418</ymin>
			<xmax>3572</xmax>
			<ymax>1576</ymax>
		</bndbox>
	</object>
	<object>
		<name>fore</name>
		<pose>Unspecified</pose>
		<truncated>0</truncated>
		<difficult>0</difficult>
		<bndbox>
			<xmin>2949</xmin>
			<ymin>587</ymin>
			<xmax>3074</xmax>
			<ymax>729</ymax>
		</bndbox>
	</object>
</annotation>
