<?xml version="1.0" encoding="utf-8"?>	<annotation>	
  	<folder>VOC2007</folder>	
  	<filename>levle1_146.jpg</filename>	
  	<size>	
    	<width>3112</width>	
    	<height>3456</height>	
    	<depth>3</depth>	
  	</size>	
  	<object>	
    	<name>fore</name>	
    	<difficult>0</difficult>	
    	<bndbox>	
      	<xmin>1237</xmin>	
      	<ymin>1363</ymin>	
      	<xmax>1329</xmax>	
      	<ymax>1547</ymax>	
    	</bndbox>	
  	</object>	
  	<object>	
    	<name>fore</name>	
    	<difficult>0</difficult>	
    	<bndbox>	
      	<xmin>2263</xmin>	
      	<ymin>2290</ymin>	
      	<xmax>2401</xmax>	
      	<ymax>2420</ymax>	
    	</bndbox>	
  	</object>	
  	<object>	
    	<name>fore</name>	
    	<difficult>0</difficult>	
    	<bndbox>	
      	<xmin>1788</xmin>	
      	<ymin>2175</ymin>	
      	<xmax>1965</xmax>	
      	<ymax>2320</ymax>	
    	</bndbox>	
  	</object>	
  	<object>	
    	<name>fore</name>	
    	<difficult>0</difficult>	
    	<bndbox>	
      	<xmin>1781</xmin>	
      	<ymin>2512</ymin>	
      	<xmax>1903</xmax>	
      	<ymax>2635</ymax>	
    	</bndbox>	
  	</object>	
  	<object>	
    	<name>fore</name>	
    	<difficult>0</difficult>	
    	<bndbox>	
      	<xmin>1965</xmin>	
      	<ymin>2880</ymin>	
      	<xmax>2057</xmax>	
      	<ymax>2995</ymax>	
    	</bndbox>	
  	</object>	
  	<object>	
    	<name>fore</name>	
    	<difficult>0</difficult>	
    	<bndbox>	
      	<xmin>2436</xmin>	
      	<ymin>2139</ymin>	
      	<xmax>2557</xmax>	
      	<ymax>2257</ymax>	
    	</bndbox>	
  	</object>	
	</annotation>