<annotation>
	<folder>VOC2007</folder>
	<filename>levle1_424.jpg</filename>
	<source>
		<database>My Database</database>
		<annotation>VOC2007</annotation>
		<image>flickr</image>
		<flickrid>NULL</flickrid>
	</source>
	<owner>
		<flickrid>NULL</flickrid>
		<name>xiaoxianyu</name>
	</owner>
	<size>
		<width>3112</width>
		<height>3456</height>
		<depth>3</depth>
	</size>
	<segmented>0</segmented>
	<object>
		<name>fore</name>
		<pose>Unspecified</pose>
		<truncated>0</truncated>
		<difficult>0</difficult>
		<bndbox>
			<xmin>738</xmin>
			<ymin>2160</ymin>
			<xmax>838</xmax>
			<ymax>2274</ymax>
		</bndbox>
	</object>
	<object>
		<name>fore</name>
		<pose>Unspecified</pose>
		<truncated>0</truncated>
		<difficult>0</difficult>
		<bndbox>
			<xmin>631</xmin>
			<ymin>2022</ymin>
			<xmax>777</xmax>
			<ymax>2175</ymax>
		</bndbox>
	</object>
	<object>
		<name>fore</name>
		<pose>Unspecified</pose>
		<truncated>0</truncated>
		<difficult>0</difficult>
		<bndbox>
			<xmin>332</xmin>
			<ymin>2466</ymin>
			<xmax>470</xmax>
			<ymax>2627</ymax>
		</bndbox>
	</object>
	<object>
		<name>fore</name>
		<pose>Unspecified</pose>
		<truncated>0</truncated>
		<difficult>0</difficult>
		<bndbox>
			<xmin>547</xmin>
			<ymin>2451</ymin>
			<xmax>738</xmax>
			<ymax>2543</ymax>
		</bndbox>
	</object>
	<object>
		<name>fore</name>
		<pose>Unspecified</pose>
		<truncated>0</truncated>
		<difficult>0</difficult>
		<bndbox>
			<xmin>585</xmin>
			<ymin>2573</ymin>
			<xmax>692</xmax>
			<ymax>2688</ymax>
		</bndbox>
	</object>
	<object>
		<name>fore</name>
		<pose>Unspecified</pose>
		<truncated>0</truncated>
		<difficult>0</difficult>
		<bndbox>
			<xmin>823</xmin>
			<ymin>2543</ymin>
			<xmax>945</xmax>
			<ymax>2704</ymax>
		</bndbox>
	</object>
	<object>
		<name>fore</name>
		<pose>Unspecified</pose>
		<truncated>0</truncated>
		<difficult>0</difficult>
		<bndbox>
			<xmin>1750</xmin>
			<ymin>734</ymin>
			<xmax>1965</xmax>
			<ymax>910</ymax>
		</bndbox>
	</object>
</annotation>
