<annotation>
	<folder>VOC2007</folder>
	<filename>levle1_192.jpg</filename>
	<source>
		<database>My Database</database>
		<annotation>VOC2007</annotation>
		<image>flickr</image>
		<flickrid>NULL</flickrid>
	</source>
	<owner>
		<flickrid>NULL</flickrid>
		<name>xiaoxianyu</name>
	</owner>
	<size>
		<width>3112</width>
		<height>3456</height>
		<depth>3</depth>
	</size>
	<segmented>0</segmented>
	<object>
		<name>fore</name>
		<pose>Unspecified</pose>
		<truncated>0</truncated>
		<difficult>0</difficult>
		<bndbox>
			<xmin>1428</xmin>
			<ymin>359</ymin>
			<xmax>1558</xmax>
			<ymax>497</ymax>
		</bndbox>
	</object>
	<object>
		<name>fore</name>
		<pose>Unspecified</pose>
		<truncated>0</truncated>
		<difficult>0</difficult>
		<bndbox>
			<xmin>2271</xmin>
			<ymin>826</ymin>
			<xmax>2455</xmax>
			<ymax>1025</ymax>
		</bndbox>
	</object>
	<object>
		<name>fore</name>
		<pose>Unspecified</pose>
		<truncated>0</truncated>
		<difficult>0</difficult>
		<bndbox>
			<xmin>1566</xmin>
			<ymin>2979</ymin>
			<xmax>1727</xmax>
			<ymax>3156</ymax>
		</bndbox>
	</object>
	<object>
		<name>fore</name>
		<pose>Unspecified</pose>
		<truncated>0</truncated>
		<difficult>0</difficult>
		<bndbox>
			<xmin>1451</xmin>
			<ymin>3002</ymin>
			<xmax>1551</xmax>
			<ymax>3140</ymax>
		</bndbox>
	</object>
	<object>
		<name>fore</name>
		<pose>Unspecified</pose>
		<truncated>0</truncated>
		<difficult>0</difficult>
		<bndbox>
			<xmin>2225</xmin>
			<ymin>2213</ymin>
			<xmax>2371</xmax>
			<ymax>2374</ymax>
		</bndbox>
	</object>
	<object>
		<name>fore</name>
		<pose>Unspecified</pose>
		<truncated>0</truncated>
		<difficult>0</difficult>
		<bndbox>
			<xmin>1229</xmin>
			<ymin>1861</ymin>
			<xmax>1336</xmax>
			<ymax>1983</ymax>
		</bndbox>
	</object>
	<object>
		<name>fore</name>
		<pose>Unspecified</pose>
		<truncated>0</truncated>
		<difficult>0</difficult>
		<bndbox>
			<xmin>1405</xmin>
			<ymin>1838</ymin>
			<xmax>1551</xmax>
			<ymax>2006</ymax>
		</bndbox>
	</object>
	<object>
		<name>fore</name>
		<pose>Unspecified</pose>
		<truncated>0</truncated>
		<difficult>0</difficult>
		<bndbox>
			<xmin>1244</xmin>
			<ymin>1592</ymin>
			<xmax>1359</xmax>
			<ymax>1730</ymax>
		</bndbox>
	</object>
</annotation>
