<?xml version="1.0" encoding="utf-8"?>	<annotation>	
  	<folder>VOC2007</folder>	
  	<filename>levle2_83.jpg</filename>	
  	<size>	
    	<width>3112</width>	
    	<height>3456</height>	
    	<depth>3</depth>	
  	</size>	
  	<object>	
    	<name>fore</name>	
    	<difficult>0</difficult>	
    	<bndbox>	
      	<xmin>1367</xmin>	
      	<ymin>1815</ymin>	
      	<xmax>1474</xmax>	
      	<ymax>1953</ymax>	
    	</bndbox>	
  	</object>	
  	<object>	
    	<name>fore</name>	
    	<difficult>0</difficult>	
    	<bndbox>	
      	<xmin>1451</xmin>	
      	<ymin>3071</ymin>	
      	<xmax>1604</xmax>	
      	<ymax>3217</ymax>	
    	</bndbox>	
  	</object>	
  	<object>	
    	<name>fore</name>	
    	<difficult>0</difficult>	
    	<bndbox>	
      	<xmin>1819</xmin>	
      	<ymin>512</ymin>	
      	<xmax>1911</xmax>	
      	<ymax>650</ymax>	
    	</bndbox>	
  	</object>	
  	<object>	
    	<name>fore</name>	
    	<difficult>0</difficult>	
    	<bndbox>	
      	<xmin>1520</xmin>	
      	<ymin>290</ymin>	
      	<xmax>1681</xmax>	
      	<ymax>420</ymax>	
    	</bndbox>	
  	</object>	
  	<object>	
    	<name>fore</name>	
    	<difficult>0</difficult>	
    	<bndbox>	
      	<xmin>1604</xmin>	
      	<ymin>711</ymin>	
      	<xmax>1773</xmax>	
      	<ymax>895</ymax>	
    	</bndbox>	
  	</object>	
  	<object>	
    	<name>fore</name>	
    	<difficult>0</difficult>	
    	<bndbox>	
      	<xmin>156</xmin>	
      	<ymin>1485</ymin>	
      	<xmax>294</xmax>	
      	<ymax>1654</ymax>	
    	</bndbox>	
  	</object>	
  	<object>	
    	<name>fore</name>	
    	<difficult>0</difficult>	
    	<bndbox>	
      	<xmin>746</xmin>	
      	<ymin>2198</ymin>	
      	<xmax>876</xmax>	
      	<ymax>2351</ymax>	
    	</bndbox>	
  	</object>	
  	<object>	
    	<name>fore</name>	
    	<difficult>0</difficult>	
    	<bndbox>	
      	<xmin>815</xmin>	
      	<ymin>2068</ymin>	
      	<xmax>1037</xmax>	
      	<ymax>2251</ymax>	
    	</bndbox>	
  	</object>	
  	<object>	
    	<name>fore</name>	
    	<difficult>0</difficult>	
    	<bndbox>	
      	<xmin>1068</xmin>	
      	<ymin>2144</ymin>	
      	<xmax>1290</xmax>	
      	<ymax>2297</ymax>	
    	</bndbox>	
  	</object>	
  	<object>	
    	<name>fore</name>	
    	<difficult>0</difficult>	
    	<bndbox>	
      	<xmin>1091</xmin>	
      	<ymin>1876</ymin>	
      	<xmax>1206</xmax>	
      	<ymax>2014</ymax>	
    	</bndbox>	
  	</object>	
  	<object>	
    	<name>fore</name>	
    	<difficult>0</difficult>	
    	<bndbox>	
      	<xmin>1581</xmin>	
      	<ymin>1792</ymin>	
      	<xmax>1735</xmax>	
      	<ymax>1999</ymax>	
    	</bndbox>	
  	</object>	
  	<object>	
    	<name>fore</name>	
    	<difficult>0</difficult>	
    	<bndbox>	
      	<xmin>1758</xmin>	
      	<ymin>1700</ymin>	
      	<xmax>1934</xmax>	
      	<ymax>1891</ymax>	
    	</bndbox>	
  	</object>	
  	<object>	
    	<name>fore</name>	
    	<difficult>0</difficult>	
    	<bndbox>	
      	<xmin>478</xmin>	
      	<ymin>2573</ymin>	
      	<xmax>647</xmax>	
      	<ymax>2757</ymax>	
    	</bndbox>	
  	</object>	
  	<object>	
    	<name>fore</name>	
    	<difficult>0</difficult>	
    	<bndbox>	
      	<xmin>539</xmin>	
      	<ymin>2865</ymin>	
      	<xmax>723</xmax>	
      	<ymax>3064</ymax>	
    	</bndbox>	
  	</object>	
  	<object>	
    	<name>fore</name>	
    	<difficult>0</difficult>	
    	<bndbox>	
      	<xmin>1566</xmin>	
      	<ymin>2213</ymin>	
      	<xmax>1750</xmax>	
      	<ymax>2343</ymax>	
    	</bndbox>	
  	</object>	
  	<object>	
    	<name>fore</name>	
    	<difficult>0</difficult>	
    	<bndbox>	
      	<xmin>1045</xmin>	
      	<ymin>520</ymin>	
      	<xmax>1229</xmax>	
      	<ymax>688</ymax>	
    	</bndbox>	
  	</object>	
  	<object>	
    	<name>fore</name>	
    	<difficult>0</difficult>	
    	<bndbox>	
      	<xmin>1390</xmin>	
      	<ymin>481</ymin>	
      	<xmax>1520</xmax>	
      	<ymax>658</ymax>	
    	</bndbox>	
  	</object>	
  	<object>	
    	<name>fore</name>	
    	<difficult>0</difficult>	
    	<bndbox>	
      	<xmin>754</xmin>	
      	<ymin>1884</ymin>	
      	<xmax>884</xmax>	
      	<ymax>2052</ymax>	
    	</bndbox>	
  	</object>	
  	<object>	
    	<name>fore</name>	
    	<difficult>0</difficult>	
    	<bndbox>	
      	<xmin>360</xmin>	
      	<ymin>2670</ymin>	
      	<xmax>560</xmax>	
      	<ymax>2815</ymax>	
    	</bndbox>	
  	</object>	
  	<object>	
    	<name>fore</name>	
    	<difficult>0</difficult>	
    	<bndbox>	
      	<xmin>1046</xmin>	
      	<ymin>2291</ymin>	
      	<xmax>1205</xmax>	
      	<ymax>2432</ymax>	
    	</bndbox>	
  	</object>	
  	<object>	
    	<name>fore</name>	
    	<difficult>0</difficult>	
    	<bndbox>	
      	<xmin>1922</xmin>	
      	<ymin>1919</ymin>	
      	<xmax>2033</xmax>	
      	<ymax>2053</ymax>	
    	</bndbox>	
  	</object>	
	</annotation>