<annotation>
	<folder>VOC2007</folder>
	<filename>levle1_264.jpg</filename>
	<source>
		<database>My Database</database>
		<annotation>VOC2007</annotation>
		<image>flickr</image>
		<flickrid>NULL</flickrid>
	</source>
	<owner>
		<flickrid>NULL</flickrid>
		<name>xiaoxianyu</name>
	</owner>
	<size>
		<width>5184</width>
		<height>3456</height>
		<depth>3</depth>
	</size>
	<segmented>0</segmented>
	<object>
		<name>fore</name>
		<pose>Unspecified</pose>
		<truncated>0</truncated>
		<difficult>0</difficult>
		<bndbox>
			<xmin>1805</xmin>
			<ymin>1108</ymin>
			<xmax>1858</xmax>
			<ymax>1204</ymax>
		</bndbox>
	</object>
	<object>
		<name>fore</name>
		<pose>Unspecified</pose>
		<truncated>0</truncated>
		<difficult>0</difficult>
		<bndbox>
			<xmin>1911</xmin>
			<ymin>1073</ymin>
			<xmax>1981</xmax>
			<ymax>1161</ymax>
		</bndbox>
	</object>
	<object>
		<name>fore</name>
		<pose>Unspecified</pose>
		<truncated>0</truncated>
		<difficult>0</difficult>
		<bndbox>
			<xmin>2410</xmin>
			<ymin>1011</ymin>
			<xmax>2542</xmax>
			<ymax>1108</ymax>
		</bndbox>
	</object>
	<object>
		<name>fore</name>
		<pose>Unspecified</pose>
		<truncated>0</truncated>
		<difficult>0</difficult>
		<bndbox>
			<xmin>2332</xmin>
			<ymin>1959</ymin>
			<xmax>2454</xmax>
			<ymax>2073</ymax>
		</bndbox>
	</object>
	<object>
		<name>fore</name>
		<pose>Unspecified</pose>
		<truncated>0</truncated>
		<difficult>0</difficult>
		<bndbox>
			<xmin>2472</xmin>
			<ymin>1915</ymin>
			<xmax>2560</xmax>
			<ymax>2003</ymax>
		</bndbox>
	</object>
	<object>
		<name>fore</name>
		<pose>Unspecified</pose>
		<truncated>0</truncated>
		<difficult>0</difficult>
		<bndbox>
			<xmin>2542</xmin>
			<ymin>1985</ymin>
			<xmax>2665</xmax>
			<ymax>2108</ymax>
		</bndbox>
	</object>
	<object>
		<name>fore</name>
		<pose>Unspecified</pose>
		<truncated>0</truncated>
		<difficult>0</difficult>
		<bndbox>
			<xmin>2744</xmin>
			<ymin>1818</ymin>
			<xmax>2840</xmax>
			<ymax>1897</ymax>
		</bndbox>
	</object>
	<object>
		<name>fore</name>
		<pose>Unspecified</pose>
		<truncated>0</truncated>
		<difficult>0</difficult>
		<bndbox>
			<xmin>2218</xmin>
			<ymin>2389</ymin>
			<xmax>2349</xmax>
			<ymax>2529</ymax>
		</bndbox>
	</object>
</annotation>
